oli/__init__.py
oli/run.py
oli/lib/__init__.py
oli/lib/command.py
oli/lib/linux_process.py
oli/linux/Folding@Home.py
oli/linux/Netdata.py
oli/linux/__init__.py
oli/linux/linux.py
oli/macos/Development-setup.py
oli/macos/Homebrew.py
oli/macos/Netdata.py
oli/macos/Oh-my-zsh.py
oli/macos/Xcode.py
oli/macos/__init__.py
oli/macos/command.py
oli/macos/mac.py
oli/macos/run_process.py
oli-0.0.21.dist-info/METADATA
oli-0.0.21.dist-info/WHEEL
oli-0.0.21.dist-info/entry_points.txt
oli-0.0.21.dist-info/top_level.txt
oli-0.0.21.dist-info/RECORD
