Metadata-Version: 2.1
Name: oli
Version: 0.0.21
Summary: One Liner Installer for Linux & MacOs
Home-page: https://github.com/StanGirard/OneLiners
Author: StanGirard
Author-email: stan@primates.dev
License: UNKNOWN
Platform: UNKNOWN
Classifier: Programming Language :: Python :: 3
Classifier: License :: OSI Approved :: MIT License
Classifier: Operating System :: OS Independent
Requires-Python: >=3.6
